[
    {
      "id": 1,
      "name": "Alice",
      "preference": "Music",
      "bio": "Loves playing the guitar and singing.",
      "image": "images/cat1.png"
    },
    {
      "id": 2,
      "name": "Bob",
      "preference": "Sports",
      "bio": "Avid basketball player and fitness enthusiast.",
      "image": "images/cat2.png"
    },
    {
      "id": 3,
      "name": "Charlie",
      "preference": "Math",
      "bio": "Exploring new places and cultures is my passion.",
      "image": "images/cat3.png"
    },
    {
        "id": 4,
        "name": "Steven",
        "preference": "Technology",
        "bio": "I really like to run and go outside.",
        "image": "images/cat3.png"
      },
      {
        "id": 5,
        "name": "Kyle",
        "preference": "Technology",
        "bio": "I love to be healthy and eat vegetables.",
        "image": "images/cat3.png"
      },
      {
        "id": 6,
        "name": "Michael",
        "preference": "Technology",
        "bio": "Hiking is my favorite hobby.",
        "image": "images/cat3.png"
      }
  ]
  